{
  "seed": "standalone-create.json",
  "generatedBy": "scripts/adapt-seed-to-043.js — GENERATED, do not hand-edit; rerun after editing the 0.45 seed",
  "counts": {
    "renames": 0,
    "downstamps": 10,
    "flattenedStyles": 0,
    "droppedProps": 6,
    "warnings": 0
  },
  "renames": [],
  "downstamps": [
    {
      "seed": "standalone-create.json",
      "component": "container:container1",
      "from": 7,
      "to": 6
    },
    {
      "seed": "standalone-create.json",
      "component": "text://*TITLE*//",
      "from": "(unset)",
      "to": 2
    },
    {
      "seed": "standalone-create.json",
      "component": "validationErrors:validationErrors",
      "from": "1",
      "to": 0
    },
    {
      "seed": "standalone-create.json",
      "component": "columns:detailsPanel",
      "from": "(unset)",
      "to": 2
    },
    {
      "seed": "standalone-create.json",
      "component": "textField:firstName",
      "from": "(unset)",
      "to": 5
    },
    {
      "seed": "standalone-create.json",
      "component": "textField:lastName",
      "from": "(unset)",
      "to": 5
    },
    {
      "seed": "standalone-create.json",
      "component": "textField:middleName",
      "from": "(unset)",
      "to": 5
    },
    {
      "seed": "standalone-create.json",
      "component": "textField:emailAddress1",
      "from": "(unset)",
      "to": 5
    },
    {
      "seed": "standalone-create.json",
      "component": "textField:mobileNumber1",
      "from": "(unset)",
      "to": 5
    },
    {
      "seed": "standalone-create.json",
      "component": "buttonGroup:formActions",
      "from": 15,
      "to": 10
    }
  ],
  "flattenedStyles": [],
  "droppedProps": [
    {
      "seed": "standalone-create.json",
      "component": "container:container1",
      "prop": "labelAlign",
      "value": "\"right\""
    },
    {
      "seed": "standalone-create.json",
      "component": "container:container1",
      "prop": "isDynamic",
      "value": "false"
    },
    {
      "seed": "standalone-create.json",
      "component": "text://*TITLE*//",
      "prop": "hideLabel",
      "value": "true"
    },
    {
      "seed": "standalone-create.json",
      "component": "text://*TITLE*//",
      "prop": "fontWeight",
      "value": "\"600\""
    },
    {
      "seed": "standalone-create.json",
      "component": "validationErrors:validationErrors",
      "prop": "isDynamic",
      "value": "false"
    },
    {
      "seed": "standalone-create.json",
      "component": "validationErrors:validationErrors",
      "prop": "labelAlign",
      "value": "\"right\""
    }
  ],
  "warnings": []
}
