{
  "archetype": "modal-dialog",
  "source": "pd-assetmanagement2 package20260713_1619.shaconfig",
  "extracted": "2026-07-22",
  "markup": {
    "components": [
      {
        "id": "c6e45597-67ca-477a-b354-8dacb3644944",
        "type": "container",
        "version": 6,
        "propertyName": "canvas",
        "componentName": "canvas",
        "direction": "vertical",
        "flexDirection": "column",
        "display": "flex",
        "hidden": false,
        "desktop": {
          "dimensions": {
            "width": "100%"
          }
        },
        "tablet": {},
        "mobile": {},
        "components": [
          {
            "id": "08d3c739-27c7-47f3-8d33-cc8dfe66acd5",
            "type": "validationErrors",
            "version": 0,
            "propertyName": "validationErrors",
            "componentName": "validationErrors",
            "parentId": "c6e45597-67ca-477a-b354-8dacb3644944"
          },
          {
            "desktop": {
              "dimensions": {
                "width": "100%"
              }
            },
            "tablet": {},
            "mobile": {},
            "parentId": "c6e45597-67ca-477a-b354-8dacb3644944",
            "type": "dropdown",
            "version": 11,
            "propertyName": "dispoNotFound",
            "componentName": "dispoNotFound",
            "label": "Disposition",
            "labelAlign": "left",
            "hideLabel": false,
            "isDynamic": false,
            "mode": "single",
            "dataSourceType": "values",
            "valueFormat": "simple",
            "editMode": "editable",
            "values": [
              {
                "id": "nf-located",
                "label": "Located on recount",
                "value": "Located on recount"
              },
              {
                "id": "nf-lost",
                "label": "Mark Lost/Stolen - write-off (finance)",
                "value": "Mark Lost/Stolen - write-off (finance)"
              }
            ],
            "hidden": {
              "_mode": "code",
              "_code": "return data.varianceType!==1;"
            },
            "id": "17116ca2-7edf-462f-aab9-8043eb97e026"
          },
          {
            "desktop": {
              "dimensions": {
                "width": "100%"
              }
            },
            "tablet": {},
            "mobile": {},
            "parentId": "c6e45597-67ca-477a-b354-8dacb3644944",
            "id": "c5f52326-3fb1-4d4f-9911-e766361f8daa",
            "type": "autocomplete",
            "version": 8,
            "propertyName": "foundLocation",
            "componentName": "foundLocation",
            "label": "Update location (optional)",
            "hideLabel": false,
            "editMode": "editable",
            "dataSourceType": "entitiesList",
            "entityType": "Shesha.Domain.Site",
            "entityTypeShortAlias": "Shesha.Domain.Site",
            "valueFormat": "entityReference",
            "useRawValues": false,
            "mode": "single",
            "hidden": {
              "_mode": "code",
              "_code": "return !(data.varianceType===1 && data.dispoNotFound==='Located on recount');"
            }
          },
          {
            "desktop": {
              "dimensions": {
                "width": "100%"
              }
            },
            "tablet": {},
            "mobile": {},
            "parentId": "c6e45597-67ca-477a-b354-8dacb3644944",
            "type": "dropdown",
            "version": 11,
            "propertyName": "dispoLocation",
            "componentName": "dispoLocation",
            "label": "Disposition",
            "labelAlign": "left",
            "hideLabel": false,
            "isDynamic": false,
            "mode": "single",
            "dataSourceType": "values",
            "valueFormat": "simple",
            "editMode": "editable",
            "values": [
              {
                "id": "fe4ef605-a8e6-4dce-90c0-24cf0481b1f4",
                "label": "Correct Register",
                "value": "Correct Register"
              },
              {
                "id": "bffff211-e337-4780-8ccd-a05500781d0c",
                "label": "Initiate Formal transfer",
                "value": "Initiate Formal transfer"
              }
            ],
            "hidden": {
              "_mode": "code",
              "_code": "return data.varianceType!==2;"
            },
            "id": "236d01e0-215c-455c-a4a2-5c711c1e4d97"
          },
          {
            "desktop": {
              "dimensions": {
                "width": "100%"
              }
            },
            "tablet": {},
            "mobile": {},
            "parentId": "c6e45597-67ca-477a-b354-8dacb3644944",
            "type": "dropdown",
            "version": 11,
            "propertyName": "dispoCustodian",
            "componentName": "dispoCustodian",
            "label": "Disposition",
            "labelAlign": "left",
            "hideLabel": false,
            "isDynamic": false,
            "mode": "single",
            "dataSourceType": "values",
            "valueFormat": "simple",
            "editMode": "editable",
            "values": [
              {
                "id": "38bdf729-0445-445a-98fe-99a8e7c791c6",
                "label": "Correct custodian (write history)",
                "value": "Correct custodian (write history)"
              },
              {
                "id": "821360e2-fd9a-4b2e-a0ac-78366ee84820",
                "label": "Initiate Formal transfer",
                "value": "Initiate Formal transfer"
              }
            ],
            "hidden": {
              "_mode": "code",
              "_code": "return data.varianceType!==3;"
            },
            "id": "363cd5d9-f461-4e50-b582-5d89f9c57cf9"
          },
          {
            "desktop": {
              "dimensions": {
                "width": "100%"
              }
            },
            "tablet": {},
            "mobile": {},
            "parentId": "c6e45597-67ca-477a-b354-8dacb3644944",
            "type": "dropdown",
            "version": 11,
            "propertyName": "dispoCondition",
            "componentName": "dispoCondition",
            "label": "Disposition",
            "labelAlign": "left",
            "hideLabel": false,
            "isDynamic": false,
            "mode": "single",
            "dataSourceType": "values",
            "valueFormat": "simple",
            "editMode": "editable",
            "values": [
              {
                "id": "cond-update-only",
                "label": "Update condition only",
                "value": "Update condition only"
              }
            ],
            "hidden": {
              "_mode": "code",
              "_code": "return data.varianceType!==4;"
            },
            "id": "ea1126b7-3a57-47c6-8e0b-f49715ce5327"
          },
          {
            "desktop": {
              "dimensions": {
                "width": "100%"
              },
              "font": {
                "size": 12,
                "weight": "600",
                "color": "#1A3E6F",
                "type": "Segoe UI"
              },
              "stylingBox": "{\"marginBottom\":\"4px\"}"
            },
            "tablet": {},
            "mobile": {},
            "parentId": "c6e45597-67ca-477a-b354-8dacb3644944",
            "id": "ecde381d-ae76-4585-8914-54e4ebc4b4d4",
            "type": "text",
            "version": 2,
            "propertyName": "transferTypeNote",
            "componentName": "transferTypeNote",
            "contentDisplay": "content",
            "textType": "span",
            "dataType": "string",
            "textAlign": "start",
            "padding": "none",
            "content": {
              "_mode": "code",
              "_code": "return 'Transfer type (auto): '+(data.varianceType===2?'Location Change':(data.varianceType===3?'Custodian change':''));"
            },
            "hidden": {
              "_mode": "code",
              "_code": "return !((data.varianceType===2 && data.dispoLocation==='Initiate Formal transfer') || (data.varianceType===3 && data.dispoCustodian==='Initiate Formal transfer'));"
            }
          },
          {
            "desktop": {
              "dimensions": {
                "width": "100%"
              }
            },
            "tablet": {},
            "mobile": {},
            "parentId": "c6e45597-67ca-477a-b354-8dacb3644944",
            "type": "autocomplete",
            "version": 8,
            "propertyName": "targetLocation",
            "componentName": "targetLocation",
            "label": "Destination location",
            "hideLabel": false,
            "editMode": "editable",
            "dataSourceType": "entitiesList",
            "entityType": "Shesha.Domain.Site",
            "entityTypeShortAlias": "Shesha.Domain.Site",
            "valueFormat": "entityReference",
            "useRawValues": false,
            "mode": "single",
            "hidden": {
              "_mode": "code",
              "_code": "return !(data.varianceType===2 && data.dispoLocation==='Initiate Formal transfer');"
            },
            "id": "78fbc59b-6462-4386-8a61-d1347075f705"
          },
          {
            "desktop": {
              "dimensions": {
                "width": "100%"
              }
            },
            "tablet": {},
            "mobile": {},
            "parentId": "c6e45597-67ca-477a-b354-8dacb3644944",
            "type": "autocomplete",
            "version": 8,
            "propertyName": "newCustodian",
            "componentName": "newCustodian",
            "label": "New custodian",
            "hideLabel": false,
            "editMode": "editable",
            "dataSourceType": "entitiesList",
            "entityType": "Shesha.Domain.Person",
            "entityTypeShortAlias": "Shesha.Domain.Person",
            "valueFormat": "entityReference",
            "useRawValues": false,
            "mode": "single",
            "hidden": {
              "_mode": "code",
              "_code": "return !(data.varianceType===3 && data.dispoCustodian==='Initiate Formal transfer');"
            },
            "id": "1d4ac371-cfff-4f42-8def-285c27017e47"
          },
          {
            "desktop": {
              "dimensions": {
                "width": "100%"
              }
            },
            "tablet": {},
            "mobile": {},
            "parentId": "c6e45597-67ca-477a-b354-8dacb3644944",
            "id": "a54cd394-bcc2-41f7-bd8c-1b30742858a6",
            "type": "autocomplete",
            "version": 8,
            "propertyName": "toCostCentre",
            "componentName": "toCostCentre",
            "label": "Destination cost centre (optional)",
            "hideLabel": false,
            "editMode": "editable",
            "dataSourceType": "entitiesList",
            "entityType": "Shesha.AssetManagement.Domain.CostCentres.CostCentre",
            "entityTypeShortAlias": "Shesha.AssetManagement.Domain.CostCentres.CostCentre",
            "valueFormat": "entityReference",
            "useRawValues": false,
            "mode": "single",
            "hidden": {
              "_mode": "code",
              "_code": "return !((data.varianceType===2 && data.dispoLocation==='Initiate Formal transfer') || (data.varianceType===3 && data.dispoCustodian==='Initiate Formal transfer'));"
            }
          },
          {
            "desktop": {
              "dimensions": {
                "width": "100%"
              }
            },
            "tablet": {},
            "mobile": {},
            "parentId": "c6e45597-67ca-477a-b354-8dacb3644944",
            "type": "dropdown",
            "version": 11,
            "propertyName": "newCondition",
            "componentName": "newCondition",
            "label": "Observed condition",
            "labelAlign": "left",
            "hideLabel": false,
            "isDynamic": false,
            "mode": "single",
            "dataSourceType": "referenceList",
            "valueFormat": "simple",
            "editMode": "editable",
            "referenceListId": {
              "module": "Shesha.AssetManagement",
              "name": "ConditionCode"
            },
            "referenceListName": "ConditionCode",
            "id": "b26aae5e-36c7-48db-a7cc-435f391459c3",
            "hidden": {
              "_mode": "code",
              "_code": "return !(data.varianceType===4 && (data.dispoCondition==='Update condition only' || data.dispoCondition==='Update condition only + raise maintenance'));"
            }
          },
          {
            "desktop": {
              "dimensions": {
                "width": "100%"
              }
            },
            "tablet": {},
            "mobile": {},
            "parentId": "c6e45597-67ca-477a-b354-8dacb3644944",
            "type": "dropdown",
            "version": 11,
            "propertyName": "disposalMethod",
            "componentName": "disposalMethod",
            "label": "Disposal method",
            "labelAlign": "left",
            "hideLabel": false,
            "isDynamic": false,
            "mode": "single",
            "dataSourceType": "referenceList",
            "valueFormat": "simple",
            "editMode": "editable",
            "referenceListId": {
              "module": "Shesha.AssetManagement",
              "name": "DisposalMethod"
            },
            "referenceListName": "DisposalMethod",
            "id": "9882827f-0f1c-45fa-804f-23d538b94867",
            "hidden": {
              "_mode": "code",
              "_code": "return !(data.varianceType===4 && data.dispoCondition==='Flag for disposal');"
            }
          },
          {
            "desktop": {
              "dimensions": {
                "width": "100%"
              }
            },
            "tablet": {},
            "mobile": {},
            "parentId": "c6e45597-67ca-477a-b354-8dacb3644944",
            "type": "textArea",
            "version": 4,
            "propertyName": "resolutionReason",
            "componentName": "resolutionReason",
            "label": "Reason",
            "editMode": "editable",
            "autoSize": false,
            "showCount": false,
            "allowClear": false,
            "id": "40524097-fa94-40b4-a702-7d60c8605599"
          },
          {
            "desktop": {
              "dimensions": {
                "width": "100%"
              }
            },
            "tablet": {},
            "mobile": {},
            "parentId": "c6e45597-67ca-477a-b354-8dacb3644944",
            "type": "dropdown",
            "version": 11,
            "propertyName": "resolutionAuthority",
            "componentName": "resolutionAuthority",
            "label": "Authority",
            "labelAlign": "left",
            "hideLabel": false,
            "isDynamic": false,
            "mode": "single",
            "dataSourceType": "referenceList",
            "valueFormat": "simple",
            "editMode": "editable",
            "referenceListId": {
              "module": "Shesha.AssetManagement",
              "name": "ReconAuthority"
            },
            "referenceListName": "ReconAuthority",
            "id": "f59d4dbc-1b6d-462e-a147-c195ad4b59f9"
          },
          {
            "id": "b141a9a8-490b-4e05-b469-da9b97d4cb1b",
            "type": "container",
            "version": 6,
            "propertyName": "footerRow",
            "componentName": "footerRow",
            "direction": "horizontal",
            "flexDirection": "row",
            "display": "flex",
            "justifyContent": "flex-end",
            "alignItems": "center",
            "hidden": false,
            "desktop": {
              "dimensions": {
                "width": "100%"
              },
              "stylingBox": "{\"marginTop\":\"16px\"}"
            },
            "tablet": {},
            "mobile": {},
            "components": [
              {
                "id": "e38dabe2-b6c9-49aa-9ea8-60c8317a5245",
                "type": "buttonGroup",
                "version": 15,
                "propertyName": "formActions",
                "componentName": "formActions",
                "label": "Form Actions",
                "hideLabel": true,
                "isInline": true,
                "editMode": "editable",
                "desktop": {},
                "tablet": {},
                "mobile": {},
                "parentId": "b141a9a8-490b-4e05-b469-da9b97d4cb1b",
                "items": [
                  {
                    "id": "0ae37dd2-e621-43bb-9987-068512011f76",
                    "itemType": "item",
                    "itemSubType": "button",
                    "sortOrder": 0,
                    "name": "btnCancel",
                    "label": "Cancel",
                    "buttonType": "default",
                    "icon": "CloseOutlined",
                    "buttonAction": "executeScript",
                    "actionConfiguration": {
                      "_type": "action-config",
                      "actionName": "Close Dialog",
                      "actionOwner": "shesha.common",
                      "version": 2,
                      "actionArguments": {
                        "showDialogResult": "false"
                      }
                    }
                  },
                  {
                    "id": "e4ffcbec-d24a-4b7b-b4fa-2891a6d38902",
                    "itemType": "item",
                    "itemSubType": "button",
                    "sortOrder": 1,
                    "name": "btnResolve",
                    "label": "Resolve",
                    "buttonType": "primary",
                    "icon": "CheckOutlined",
                    "buttonAction": "executeScript",
                    "actionConfiguration": {
                      "_type": "action-config",
                      "actionName": "Execute Script",
                      "actionOwner": "shesha.common",
                      "version": 2,
                      "actionArguments": {
                        "expression": "var refId=function(x){return x?(x.id||x):null;};\nvar vt=data.varianceType;\nvar dispo = vt===2?data.dispoLocation : (vt===3?data.dispoCustodian : (vt===4?data.dispoCondition : data.dispoNotFound));\nif(!dispo){message.error('Please select a disposition.');throw new Error('disposition required');}\nif(!data.resolutionReason){message.error('Reason is required.');throw new Error('reason required');}\nvar assetId=refId(data.asset);\nvar campId=refId(data.campaign);\nvar me=application.user.personId;\nvar a=data.asset||{};\ntry{\n  if(vt===1 && dispo==='Located on recount'){\n    var nl=refId(data.foundLocation);\n    if(nl){ await http.put('/api/dynamic/Shesha.AssetManagement/RegisteredAsset/Crud/Update',{id:assetId,location:nl}); }\n  } else if(vt===1 && dispo==='Mark Lost/Stolen - write-off (finance)'){\n    await http.put('/api/dynamic/Shesha.AssetManagement/RegisteredAsset/Crud/Update',{id:assetId,lifecycleState:12});\n  } else if(vt===2 && dispo==='Correct Register'){\n    /* Register stands: reject the verifier's proposed location change; no asset update. */\n  } else if(vt===2 && dispo==='Initiate Formal transfer'){\n    var loc2=refId(data.targetLocation)||(a.observedLocation?refId(a.observedLocation):null);\n    if(!loc2){message.error('Select the destination location.');throw new Error('loc');}\n    await http.post('/api/services/AssetManagement/Transfer/InitiateTransfer',{assetId:assetId,transferType:3,toLocationId:loc2,toCustodianId:refId(data.newCustodian),toCostCentreId:refId(data.toCostCentre),reason:data.resolutionReason,requestedById:me});\n  } else if(vt===3 && dispo==='Correct custodian (write history)'){\n    var obsCust=(data.fieldObservation && data.fieldObservation.observedCustodian)?refId(data.fieldObservation.observedCustodian):null;\n    if(obsCust){ var eaId=a.enterpriseAsset?refId(a.enterpriseAsset):null; if(eaId){ await http.put('/api/dynamic/Shesha.Enterprise/Asset/Crud/Update',{id:eaId,responsiblePerson:obsCust}); } }\n    /* no field-observed custodian captured as a linked person: resolution recorded (audited), no FK change. */\n  } else if(vt===3 && dispo==='Initiate Formal transfer'){\n    var cust2=refId(data.newCustodian);\n    if(!cust2){message.error('Select the new custodian.');throw new Error('cust');}\n    var curLoc=a.location?refId(a.location):null;\n    await http.post('/api/services/AssetManagement/Transfer/InitiateTransfer',{assetId:assetId,transferType:1,toCustodianId:cust2,toLocationId:curLoc,toCostCentreId:refId(data.toCostCentre),reason:data.resolutionReason,requestedById:me});\n  } else if(vt===4 && (dispo==='Update condition only' || dispo==='Update condition only + raise maintenance')){\n    var cond=(data.newCondition===''||data.newCondition==null)?(a.observedCondition?a.observedCondition:null):data.newCondition;\n    if(cond==null||cond===0){message.error('Select the observed condition.');throw new Error('cond');}\n    await http.put('/api/dynamic/Shesha.AssetManagement/RegisteredAsset/Crud/Update',{id:assetId,conditionCode:cond});\n  } else if(vt===4 && dispo==='Flag for disposal'){\n    var method=(data.disposalMethod===''||data.disposalMethod==null)?7:data.disposalMethod;\n    await http.post('/api/services/AssetManagement/Disposal/Nominate',{assetId:assetId,reason:data.resolutionReason,method:method});\n  }\n}catch(e){message.error('The correction could not be applied: '+((e&&e.message)?e.message:'error'));throw e;}\nvar fin=!!data.financiallySignificant;\nif(vt===4 && dispo==='Flag impairment (finance)') fin=true;\nif(vt===1 && dispo==='Mark Lost/Stolen - write-off (finance)') fin=true;\nvar payload={id:data.id,campaign:campId,varianceType:vt,financiallySignificant:fin,resolved:true,resolutionDisposition:dispo,resolutionReason:data.resolutionReason,resolvedBy:me,resolvedDate:new Date().toISOString()};\nif(data.resolutionAuthority) payload.resolutionAuthority=data.resolutionAuthority;\nif(data.asset) payload.asset=assetId;\ntry{await http.put('/api/dynamic/Shesha.AssetManagement/Variance/Crud/Update',payload);}catch(e){message.error('The action was applied but saving the resolution failed. Please retry.');throw e;}\nmessage.success('Variance resolved.');"
                      },
                      "handleSuccess": true,
                      "onSuccess": {
                        "_type": "action-config",
                        "actionName": "Close Dialog",
                        "actionOwner": "shesha.common",
                        "version": 2,
                        "actionArguments": {
                          "showDialogResult": "true"
                        }
                      }
                    }
                  }
                ]
              }
            ],
            "parentId": "c6e45597-67ca-477a-b354-8dacb3644944"
          }
        ],
        "parentId": "root"
      }
    ],
    "formSettings": {
      "modelType": "Shesha.AssetManagement.Domain.Variances.Variance",
      "dataLoaderType": "none",
      "dataSubmitType": "none",
      "dataSubmitterType": "none",
      "layout": {
        "labelCol": {
          "span": 24
        },
        "wrapperCol": {
          "span": 24
        }
      },
      "labelCol": {
        "span": 24
      },
      "wrapperCol": {
        "span": 24
      },
      "access": null,
      "permissions": null,
      "version": 6,
      "onBeforeDataLoad": "form.setFieldsValue({...form.formArguments});",
      "onAfterDataLoad": "const run = async () => {\n  try {\n    var vid = data && data.id ? data.id : null;\n    if (!vid) return;\n    var props = 'id,detail,observedValue,custodianName,varianceType,financiallySignificant,resolved,resolutionDisposition,resolutionReason,resolutionAuthority,campaign{id},fieldObservation{id,observedLocation{id,_displayName},observedCondition,observedCustodian{id,_displayName}},asset{id,location{id,_displayName},observedLocation{id,_displayName},conditionCode,observedCondition,enterpriseAsset{id,responsiblePerson{id,_displayName}}}';\n    var res = await http.get('/api/dynamic/Shesha.AssetManagement/Variance/Crud/Get?id=' + vid + '&properties=' + encodeURIComponent(props));\n    var v = res && res.data && res.data.result;\n    if (v && form && form.setFieldsValue) form.setFieldsValue(v);\n    if (v && v.resolutionDisposition) {\n      var dispo = {};\n      if (v.varianceType === 1) dispo.dispoNotFound = v.resolutionDisposition;\n      else if (v.varianceType === 2) dispo.dispoLocation = v.resolutionDisposition;\n      else if (v.varianceType === 3) dispo.dispoCustodian = v.resolutionDisposition;\n      else if (v.varianceType === 4) dispo.dispoCondition = v.resolutionDisposition;\n      if (Object.keys(dispo).length) form.setFieldsValue(dispo);\n    }\n    if (v && !v.resolutionAuthority) form.setFieldsValue({ resolutionAuthority: null });\n    // Prefill the resolution inputs with the values the verifier submitted, so the reconciler\n    // only confirms or overrides them. Field-app capture (fieldObservation) is the primary source;\n    // the asset's pending-sign-off fields / the captured name string are the fallback.\n    if (v) {\n      var fo = v.fieldObservation || {};\n      var a = v.asset || {};\n      var patch = {};\n      var obsLoc = fo.observedLocation || a.observedLocation;\n      if (obsLoc) patch.targetLocation = obsLoc;\n      var obsCond = (fo.observedCondition != null && fo.observedCondition !== 0) ? fo.observedCondition : ((a.observedCondition != null && a.observedCondition !== 0) ? a.observedCondition : null);\n      if (obsCond != null) patch.newCondition = obsCond;\n      var obsCust = fo.observedCustodian || null;\n      if (!obsCust && v.varianceType === 3) {\n        var nm = v.custodianName || v.observedValue;\n        if (nm) {\n          try {\n            var flt = JSON.stringify({ '==': [{ 'var': 'fullName' }, nm] });\n            var pr = await http.get('/api/dynamic/Shesha/Person/Crud/GetAll?maxResultCount=1&properties=' + encodeURIComponent('id,fullName') + '&filter=' + encodeURIComponent(flt));\n            var items = pr && pr.data && pr.data.result && pr.data.result.items;\n            if (items && items.length) obsCust = { id: items[0].id, _displayName: items[0].fullName };\n          } catch (e) {}\n        }\n      }\n      if (obsCust) patch.newCustodian = obsCust;\n      if (Object.keys(patch).length) form.setFieldsValue(patch);\n    }\n  } catch (e) {}\n};\nreturn run();",
      "onPrepareSubmitData": null,
      "onBeforeSubmit": null,
      "onSubmitSuccess": null,
      "onSubmitFailed": null,
      "dataLoadersSettings": {
        "gql": {
          "endpointType": "default"
        },
        "custom": {}
      },
      "dataSubmittersSettings": {
        "gql": {
          "endpointType": "default"
        }
      }
    }
  }
}